uagents_adapter/__init__.py
uagents_adapter/a2a_inbound/README.md
uagents_adapter/a2a_inbound/__init__.py
uagents_adapter/a2a_inbound/adapter.py
uagents_adapter/a2a_inbound/agentverse_executor.py
uagents_adapter/a2a_inbound/cli.py
uagents_adapter/a2a_outbound/__init__.py
uagents_adapter/a2a_outbound/adapter.py
uagents_adapter/a2a_outbound/ap2/artifacts.py
uagents_adapter/a2a_outbound/ap2/bridge_mapping.py
uagents_adapter/a2a_outbound/readme.md
uagents_adapter/common/__init__.py
uagents_adapter/crewai/__init__.py
uagents_adapter/crewai/tools.py
uagents_adapter/langchain/__init__.py
uagents_adapter/langchain/agent_utils.py
uagents_adapter/langchain/tools.py
uagents_adapter/mcp/README.md
uagents_adapter/mcp/__init__.py
uagents_adapter/mcp/adapter.py
uagents_adapter/mcp/protocol.py
uagents_adapter-0.6.2.dist-info/METADATA
uagents_adapter-0.6.2.dist-info/WHEEL
uagents_adapter-0.6.2.dist-info/RECORD
