Metadata-Version: 2.4
Name: uagents-adapter
Version: 0.6.2
Summary: Adapters for uAgents to integrate with LangChain, CrewAI, MCP, and A2A
License: Apache 2.0
Keywords: uagents,agents,langchain,crewai,mcp,a2a,fetch.ai
Author: Fetch.AI Limited
Requires-Python: >=3.10,<4.0
Classifier: License :: Other/Proprietary License
Classifier: Programming Language :: Python :: 3
Classifier: Programming Language :: Python :: 3.10
Classifier: Programming Language :: Python :: 3.11
Classifier: Programming Language :: Python :: 3.12
Classifier: Programming Language :: Python :: 3.13
Classifier: Programming Language :: Python :: 3.14
Provides-Extra: a2a-inbound
Provides-Extra: a2a-outbound
Provides-Extra: all
Provides-Extra: crewai
Provides-Extra: langchain
Provides-Extra: mcp
Requires-Dist: a2a-sdk[all,sql,sqlite] (>=0.2.11) ; extra == "a2a-inbound"
Requires-Dist: a2a-sdk[all,sql,sqlite] (>=0.2.11) ; extra == "a2a-outbound"
Requires-Dist: a2a-sdk[all,sql,sqlite] (>=0.2.11) ; extra == "all"
Requires-Dist: click (>=8.0.0)
Requires-Dist: crewai (==0.203.1) ; extra == "all"
Requires-Dist: crewai (==0.203.1) ; extra == "crewai"
Requires-Dist: httpx (>=0.25.0)
Requires-Dist: langchain (>=0.3.0) ; extra == "all"
Requires-Dist: langchain (>=0.3.0) ; extra == "langchain"
Requires-Dist: langchain-core (>=0.3.52,<0.4.0) ; extra == "all"
Requires-Dist: langchain-core (>=0.3.52,<0.4.0) ; extra == "langchain"
Requires-Dist: langchain-openai (>=0.2.0) ; extra == "all"
Requires-Dist: langchain-openai (>=0.2.0) ; extra == "langchain"
Requires-Dist: mcp (>=1.8.1) ; extra == "all"
Requires-Dist: mcp (>=1.8.1) ; extra == "mcp"
Requires-Dist: openai (>=1.0.0)
Requires-Dist: pydantic (>=2.8,<3.0)
Requires-Dist: python-dotenv (>=1.0.0)
Requires-Dist: requests (>=2.32.0,<3.0)
Requires-Dist: uagents (>=0.22.3)
Requires-Dist: uvicorn (>=0.27.0)
